{
  "name": "LuxXx - Fractal Overlord Overclock ii",
  "clearFrame": false,
  "components": [
    {
      "type": "MilkDropMotion",
      "enabled": true,
      "code": {
        "init": "decay = 0.955",
        "perFrame": "zoom = 1;\nrot = 0;\ndx = 0;\ndy = 0;\nsx = 1;\nsy = 1;\nwarp = 1;\ncx = 0.5;\ncy = 0.5;\nwarp = 0;;\nvolume = 0.3*(bass+mid+att);;\nxamptarg = if(((frame%15) == (0)),min(0.25*volume*bass_att,0.5),xamptarg);;\nxamp = xamp + 0.5*(xamptarg-xamp);;\nxdir = if(((abs(xpos)) > (xamp)),-sign(xpos),if(((abs(xspeed)) < (0.1)),2*((xpos) > (0))-1,xdir));;\nxspeed = xspeed + xdir*xamp - xpos - xspeed*0.055*((abs(xpos)) < (xamp));;\nxpos = xpos + 0.001*xspeed;;\nyamptarg = if(((frame%15) == (0)),min(0.15*volume*treb_att,0.5),yamptarg);;\nyamp = yamp + 0.5*(yamptarg-yamp);;\nydir = if(((abs(ypos)) > (yamp)),-sign(ypos),if(((abs(yspeed)) < (0.1)),2*((ypos) > (0))-1,ydir));;\nyspeed = yspeed + ydir*yamp - ypos - yspeed*0.055*((abs(ypos)) < (yamp));;\nypos = ypos + 0.001*yspeed;;\nbeatrate = ((beatrate) == (0)) + (1-((beatrate) == (0)))*(((volume) < (0.01)) + (1-((volume) < (0.01)))*beatrate);;\nlastbeat = lastbeat + ((lastbeat) == (0))*time;;\nmeanbass_att = 0.1*(meanbass_att*9 + bass_att);;\npeakbass_att = max(bass_att,peakbass_att);;\nbeat = ((volume) > (0.8))*((peakbass_att - bass_att) < (0.05*peakbass_att))*((time - lastbeat) > (0.1 + 0.5*(beatrate - 0.1)));;\nbeatrate = max(if(beat,if(((time-lastbeat) < (2*beatrate)),0.1*(beatrate*9 + time - lastbeat),beatrate),beatrate),0.1);;\npeakbass_att = beat*bass_att + (1-beat)*peakbass_att*(((time - lastbeat) > (2*beatrate))*0.95 + (1-((time - lastbeat) > (2*beatrate)))*0.995);;\nlastbeat = beat*time + (1-beat)*lastbeat;;\npeakbass_att = max(peakbass_att,1.1*meanbass_att);;\nwave_x = xpos + 0.5;;\nwave_y = 1-(ypos + 0.5);;\nwave_r = 0.5 + 0.499*( 0.60*sin(0.980*time) + 0.40*sin(1.047*time) );;\nwave_g = 0.5 + 0.499*( 0.60*sin(0.835*time) + 0.40*sin(1.081*time) );;\nwave_b = 0.5 + 0.499*( 0.60*sin(0.814*time) + 0.40*sin(1.011*time) );;\nwave_mystery = -0.17 + 0.03*(0.6*sin(0.637*time) + 0.4*sin(0.949*time));;\nmv_r = if(beat, 1, ib_r);;\nmv_b = if(beat, wave_b, ib_b);;\n//mv_a = if(beat, 0.1, ib_a);;\n//ib_a = 0.015;;\nq3 = wave_mystery;;\nq1 = wave_x;;\nq2 = 1-wave_y;;\nq2 = ypos+0.5;;\nwarp=0;;\n//q2 = 1-(ypos + 0.5);;\n//q1 = 0.5;;\n//q2=0.5;;\nob_r = 1-wave_g;;\nob_b = 1-wave_r;;\nob_g = 1-wave_b;;\nmonitor = wave_y;;\nmovement =movement + 0.4*(((bass+bass_att + 0.1*pow((bass+0.6*bass_att+0.2*treb_att),3)))/fps);;\nmovement = if(((movement) > (10000)), 0, movement);;\nrot =1*sin(movement);;\ncx = wave_x;;\ncy = y_pos+0.5;;\nq8 = movement;",
        "perVertex": "myy = x-q1;;\nmyx = y-q2+0.1;;\ndx = 3*sin(q8*0.675)*(2*myx*myy);;\ndy = 3*sin(q8*0.675)*((myx*myx) - (myy*myy));"
      },
      "gridSize": 48
    },
    {
      "type": "SuperScope",
      "enabled": true,
      "drawMode": "LINES",
      "audioSource": "SPECTRUM",
      "audioChannel": "CENTER",
      "colors": [
        "#8080cc"
      ],
      "code": {
        "init": "n=256",
        "perFrame": "",
        "onBeat": "",
        "perPoint": "x=(i*2-1)*0.9; y=v*0.4"
      }
    },
    {
      "type": "Echo",
      "enabled": true,
      "zoom": 0.997,
      "alpha": 0.5,
      "orient": 1
    }
  ]
}