{
  "name": "sewn to slavish memes",
  "clearFrame": false,
  "components": [
    {
      "type": "MilkDropMotion",
      "enabled": true,
      "code": {
        "init": "decay = 0.94",
        "perFrame": "zoom = 1.11566;\nrot = 1;\ndx = 0;\ndy = 0;\nsx = 1;\nsy = 1;\nwarp = 0.01;\ncx = 0.5;\ncy = 0.5;\ndecay=0.975;;\nvol=(bass+mid+treb)*0.25;;\nvol=vol*vol;;\nmtime=mtime+vol*0.01;;\nq1=time*0.5;;\ngamma=1 + min(vol*0.8,1)*0.7",
        "perVertex": "zm=1.00;;\nsx=zm;;\nsy=zm;"
      },
      "gridSize": 48
    },
    {
      "type": "Invert",
      "enabled": true
    }
  ]
}