{
  "name": "Geiss - Terra Landing",
  "clearFrame": false,
  "components": [
    {
      "type": "CustomShader",
      "enabled": true,
      "code": { "init": "", "perFrame": "" },
      "shader": "precision mediump float;\nuniform sampler2D tSource;\nuniform float uTime;\nvarying vec2 vUv;\nvoid main() {\n  vec2 center = vec2(0.5);\n  vec2 p = vUv - center;\n  // Mode 3: terra landing - slow zoom with slight rotation\n  float scale1 = 0.90 + 0.05*sin(uTime*0.12);\n  float turn1 = 0.015 + 0.008*sin(uTime*0.18);\n  float cs = cos(turn1);\n  float sn = sin(turn1);\n  vec2 rotated = vec2(p.x*cs - p.y*sn, p.x*sn + p.y*cs);\n  vec2 uv = rotated * (1.0/scale1) + center;\n  // Horizontal wrapping\n  uv.x = fract(uv.x);\n  uv.y = clamp(uv.y, 0.0, 1.0);\n  gl_FragColor = texture2D(tSource, uv) * 0.992;\n}"
    },
    {
      "type": "SuperScope",
      "enabled": true,
      "drawMode": "LINES",
      "audioSource": "WAVEFORM",
      "audioChannel": "CENTER",
      "colors": ["#44ff88"],
      "code": {
        "init": "n=512; t=0",
        "perFrame": "t=t+0.011; vol=getspec(0,0.1,0); base=(vol*4+0.4)-0.1; cr=base*(1+0.3*sin(t*0.53+10)); cg=base*(1+0.3*sin(t*0.74+5)); cb=base*(1+0.3*sin(t*0.91))",
        "onBeat": "",
        "perPoint": "x=(i*2-1)*0.9; y=v*0.35; red=cr; green=cg; blue=cb"
      }
    }
  ]
}
